COMPS/AuthManager.py
COMPS/Client.py
COMPS/CredentialPrompt.py
COMPS/__init__.py
COMPS/__main__.py
COMPS/logging.ini
COMPS/Data/AssetCollection.py
COMPS/Data/AssetCollectionFile.py
COMPS/Data/AssetFile.py
COMPS/Data/AssetManager.py
COMPS/Data/AssetType.py
COMPS/Data/BaseEntity.py
COMPS/Data/CommissionableEntity.py
COMPS/Data/Configuration.py
COMPS/Data/Experiment.py
COMPS/Data/HpcJob.py
COMPS/Data/OutputFileMetadata.py
COMPS/Data/Priority.py
COMPS/Data/QueryCriteria.py
COMPS/Data/RelatableEntity.py
COMPS/Data/SerializableEntity.py
COMPS/Data/Simulation.py
COMPS/Data/SimulationFile.py
COMPS/Data/Suite.py
COMPS/Data/TaggableEntity.py
COMPS/Data/WorkItem.py
COMPS/Data/WorkItemFile.py
COMPS/Data/__init__.py
COMPS/Data/WorkItems/BuilderWorkItem.py
COMPS/Data/WorkItems/__init__.py
COMPS/utils/__example_utility_template__.py
COMPS/utils/__init__.py
COMPS/utils/clone_simulation.py
COMPS/utils/create_asset_collection.py
COMPS/utils/get_output_files_for_experiment.py
COMPS/utils/get_output_files_for_workitem.py
COMPS/utils/get_output_tail.py
COMPS/utils/get_status.py
COMPS/utils/get_user_info.py
COMPS/utils/main.py
COMPS/utils/rerun_failed_simulations_for_experiment.py
comps_sif_constructor/__init__.py
comps_sif_constructor/analyzers.py
comps_sif_constructor/cli.py
comps_sif_constructor/constructors.py
comps_sif_constructor/create_auth_tokens.py
comps_sif_constructor/create_sif.py
comps_sif_constructor/defaults.py
comps_sif_constructor/gather.py
comps_sif_constructor/io.py
comps_sif_constructor/launch.py
comps_sif_constructor/login.py
comps_sif_constructor/main.py
comps_sif_constructor/version.py
idmtools/__init__.py
idmtools/analysis/__init__.py
idmtools/analysis/add_analyzer.py
idmtools/analysis/analyze_manager.py
idmtools/analysis/csv_analyzer.py
idmtools/analysis/download_analyzer.py
idmtools/analysis/map_worker_entry.py
idmtools/analysis/platform_analysis_bootstrap.py
idmtools/analysis/platform_anaylsis.py
idmtools/analysis/tags_analyzer.py
idmtools/assets/__init__.py
comps_sif_constructor-0.4.0.dist-info/METADATA
comps_sif_constructor-0.4.0.dist-info/WHEEL
comps_sif_constructor-0.4.0.dist-info/entry_points.txt
comps_sif_constructor-0.4.0.dist-info/licenses/LICENSE
comps_sif_constructor-0.4.0.dist-info/RECORD
