Metadata-Version: 2.4
Name: comps-sif-constructor
Version: 0.4.0
Summary: Create a SIF file from a Singularity definition file for COMPS
Author: Katherine Rosenfeld, Kurt Frey
License-Expression: Apache-2.0
License-File: LICENSE
Requires-Python: >=3.9
Requires-Dist: backoff>=2.2.1
Requires-Dist: click>=8.1.8
Requires-Dist: coloredlogs>=15.0.1
Requires-Dist: diskcache>=5.6.3
Requires-Dist: filelock>=3.18.0
Requires-Dist: future>=1.0.0
Requires-Dist: jinja2>=3.1.6
Requires-Dist: more-itertools>=10.7.0
Requires-Dist: numpy>=2.0.2
Requires-Dist: packaging>=25.0
Requires-Dist: pandas>=2.2.3
Requires-Dist: pluggy>=1.5.0
Requires-Dist: pyyaml>=6.0.2
Requires-Dist: requests>=2.32.3
Requires-Dist: tqdm>=4.67.1
Requires-Dist: xdg>=6.0.0
